admin_buttons/__init__.py
admin_buttons/admin.py
admin_buttons/apps.py
admin_buttons/static/admin_buttons/custom_submit_row.css
admin_buttons/templates/admin_buttons/change_form.html
admin_buttons/templates/admin_buttons/submit_line.html
admin_buttons/templatetags/custom_admin.py
django_admin_more_buttons-0.0.1.dist-info/METADATA
django_admin_more_buttons-0.0.1.dist-info/WHEEL
django_admin_more_buttons-0.0.1.dist-info/licenses/LICENSE
django_admin_more_buttons-0.0.1.dist-info/RECORD
