Metadata-Version: 2.4
Name: django-admin-more-buttons
Version: 0.0.1
Summary: Add more buttons with custom behavior to your django admin's submit line.
Project-URL: Homepage, https://gitlab.com/joaoseckler/django-admin-more-buttons
Project-URL: Issues, https://gitlab.com/joaoseckler/django-admin-more-buttons/issues
Author-email: João Seckler <jseckler@riseup.net>
License-Expression: MIT
License-File: LICENSE
Classifier: Operating System :: OS Independent
Classifier: Programming Language :: Python :: 3
Requires-Python: >=3.7
